Workbook
Name Slicer_Category: #N/A
Name Slicer_City: #N/A
Name Slicer_Month: #N/A
Name Slicer_Product_name: #N/A

Sheet Customer_Master
A1: Customer ID | B1: Customer Name | C1: City
A2: C0001 | B2: Riya Sharma | C2: Delhi
A3: C0002 | B3: Arjun Mehta | C3: Mumbai
A4: C0003 | B4: Meena Joshi | C4: Mumbai
A5: C0004 | B5: Mohan Das | C5: Mumbai
A6: C0005 | B6: Riya Sharma | C6: Jaipur
A7: C0006 | B7: Amit Kumar | C7: Pune
A8: C0007 | B8: Neha Singh | C8: Lucknow
A9: C0008 | B9: Anjali Gupta | C9: Lucknow
A10: C0009 | B10: Vikas Yadav | C10: Mumbai
A11: C0010 | B11: Meena Joshi | C11: Mumbai
A12: C0011 | B12: Amit Kumar | C12: Ahmedabad
... A15: C0014 | B15: Riya Sharma | C15: Jaipur
A16: C0015 | B16: Riya Sharma
A17: C0016 | B17: Rahul Sharma | C17: Jaipur
A18: C0017 | B18: Amit Kumar | C18: Delhi
A19: C0018 | B19: Sneha Roy | C19: Mumbai
A20: C0019 | B20: Meena Joshi | C20: Noida
A21: C0020 | B21: Riya Sharma | C21: Lucknow
A22: C0021 | B22: Sneha Roy | C22: Chandigarh
A23: C0022 | B23: Meena Joshi | C23: Ahmedabad
A24: C0023 | B24: Vikas Yadav | C24: Chandigarh
A25: C0024 | B25: Karan Patel | C25: Ahmedabad
A26: C0025 | B26: Priya Verma | C26: Delhi
A27: C0026 | B27: Meena Joshi | C27: Mumbai
A28: C0027 | B28: Neha Singh | C28: Chandigarh
... A67: C0066 | B67: Karan Patel | C67: Jaipur
A68: C0067 | B68: Neha Singh
A69: C0068 | B69: Arjun Mehta | C69: Jaipur
A70: C0069 | B70: Mohan Das | C70: Ahmedabad
A71: C0070 | B71: Vikas Yadav | C71: Pune
A72: C0071 | B72: Karan Patel | C72: Jaipur
A73: C0072 | B73: Arjun Mehta | C73: Pune
A74: C0073 | B74: Vikas Yadav | C74: Delhi
A75: C0074 | B75: Riya Sharma | C75: Chandigarh
A76: C0075 | B76: Mohan Das | C76: Jaipur
A77: C0076 | B77: Rahul Sharma | C77: Jaipur
A78: C0077 | B78: Karan Patel | C78: Noida
A79: C0078 | B79: Priya Verma | C79: Jaipur
A80: C0079 | B80: Amit Kumar | C80: Mumbai
... A98: C0097 | B98: Vikas Yadav | C98: Jaipur
A99: C0098 | B99: Neha Singh
A100: C0099 | B100: Riya Sharma | C100: Pune
A101: C0100 | B101: Karan Patel | C101: Delhi
A102: C0101 | B102: Anjali Gupta | C102: Ahmedabad
A103: C0102 | B103: Meena Joshi | C103: Jaipur
A104: C0103 | B104: Mohan Das | C104: Mumbai
A105: C0104 | B105: Neha Singh | C105: Pune
A106: C0105 | B106: Sneha Roy | C106: Pune
A107: C0106 | B107: Vikas Yadav | C107: Ahmedabad
A108: C0107 | B108: Amit Kumar | C108: Lucknow
A109: C0108 | B109: Priya Verma | C109: Lucknow
A110: C0109 | B110: Neha Singh | C110: Ahmedabad
A111: C0110 | B111: Priya Verma | C111: Noida
... A153: C0152 | B153: Vikas Yadav | C153: Noida
A154: C0153 | B154: Karan Patel
A155: C0154 | B155: Karan Patel | C155: Lucknow
A156: C0155 | B156: Anjali Gupta | C156: Ahmedabad
A157: C0156 | B157: Sneha Roy | C157: Lucknow
A158: C0157 | B158: Riya Sharma | C158: Ahmedabad
A159: C0158 | B159: Amit Kumar | C159: Jaipur
A160: C0159 | B160: Meena Joshi | C160: Lucknow
A161: C0160 | B161: Sneha Roy | C161: Mumbai
A162: C0161 | B162: Sneha Roy | C162: Jaipur
A163: C0162 | B163: Riya Sharma | C163: Noida
A164: C0163 | B164: Sneha Roy | C164: Lucknow
A165: C0164 | B165: Arjun Mehta | C165: Pune
A166: C0165 | B166: Sneha Roy
A167: C0166 | B167: Karan Patel | C167: Ahmedabad
A168: C0167 | B168: Amit Kumar | C168: Mumbai
A169: C0168 | B169: Vikas Yadav | C169: Lucknow
A170: C0169 | B170: Amit Kumar | C170: Chandigarh
A171: C0170 | B171: Meena Joshi | C171: Pune
A172: C0171 | B172: Riya Sharma | C172: Mumbai
A173: C0172 | B173: Priya Verma | C173: Delhi
A174: C0173 | B174: Mohan Das | C174: Pune
A175: C0174 | B175: Sneha Roy | C175: Delhi
A176: C0175 | B176: Rahul Sharma | C176: Ahmedabad
A177: C0176 | B177: Karan Patel | C177: Ahmedabad
A178: C0177 | B178: Arjun Mehta | C178: Jaipur
... A194: C0193 | B194: Karan Patel | C194: Mumbai
A195: C0194 | B195: Mohan Das
A196: C0195 | B196: Meena Joshi | C196: Chandigarh
A197: C0196 | B197: Anjali Gupta | C197: Ahmedabad
A198: C0197 | B198: Arjun Mehta | C198: Jaipur
A199: C0198 | B199: Meena Joshi | C199: Ahmedabad
A200: C0199 | B200: Anjali Gupta | C200: Chandigarh
A201: C0200 | B201: Meena Joshi | C201: Jaipur
A202: C0201 | B202: Sneha Roy | C202: Mumbai
A203: C0202 | B203: Arjun Mehta | C203: Delhi
A204: C0203 | B204: Meena Joshi | C204: Lucknow
A205: C0204 | B205: Meena Joshi | C205: Jaipur
A206: C0205 | B206: Vikas Yadav | C206: Noida
A207: C0206 | B207: Priya Verma | C207: Lucknow
... A214: C0213 | B214: Neha Singh | C214: Jaipur
A215: C0214 | B215: Priya Verma
A216: C0215 | B216: Priya Verma | C216: Mumbai
A217: C0216 | B217: Karan Patel | C217: Ahmedabad
A218: C0217 | B218: Anjali Gupta | C218: Noida
A219: C0218 | B219: Priya Verma | C219: Noida
...

Sheet Product_Master
A1: Product ID | B1: Product Name | C1: Category | D1: Cost Price | E1: Selling Price
A2: P001 | B2: Mobile | C2: Electronics | D2: 20000 | E2: 25000
A3: P002 | B3: Mouse | C3: Accessories | D3: 500 | E3: 800
A4: P003 | B4: Keyboard | C4: Accessories | D4: 900 | E4: 1500
A5: P004 | B5: Tablet | C5: Electronics | D5: 15000 | E5: 18000
A6: P005 | B6: Mouse | C6: Accessories | D6: 500 | E6: 800
A7: P006 | B7: Laptop | C7: Electronics | D7: 42000 | E7: 50000
A8: P007 | B8: Mobile | C8: Electronics | D8: 20000 | E8: 25000
A9: P008 | B9: Tablet | C9: Electronics | D9: 15000 | E9: 18000
A10: P009 | B10: Speaker | C10: Accessories | D10: 2000 | E10: 3000
A11: P010 | B11: Monitor | C11: Accessories | D11: 9000 | E11: 12000
A12: P011 | B12: Keyboard | C12: Accessories | D12: 900 | E12: 1500
A13: P012 | B13: Keyboard | C13: Accessories | D13: 900 | E13: 1500
... A101: P100 | B101: Speaker | C101: Accessories | D101: 2000 | E101: 3000

Sheet Sales_Data
A1: Order ID | B1: Order Date | C1: Customer ID | D1: Product ID | E1: Quantity
A2: O00001 | B2: 45748 | C2: C0020 | D2: P090 | E2: 2
A3: O00002 | B3: 46015 | C3: C0142 | D3: P035 | E3: 4
A4: O00003 | B4: 45668 | C4: C0300 | D4: P072 | E4: 2
A5: O00004 | B5: 45846 | C5: C0069 | D5: P018 | E5: 5
A6: O00005 | B6: 45960 | C6: C0130 | D6: P058 | E6: 2
A7: O00006 | B7: 45796 | C7: C0282 | D7: P042 | E7: 1
A8: O00007 | B8: 45913 | C8: C0031 | D8: P016 | E8: 3
A9: O00008 | B9: 45895 | C9: C0157 | D9: P024 | E9: 1
A10: O00009 | B10: 45866 | C10: C0114 | D10: P027 | E10: 4
A11: O00010 | B11: 45853 | C11: C0218 | D11: P035 | E11: 5
A12: O00011 | B12: 45758 | C12: C0063 | D12: P032 | E12: 4
A13: O00012 | B13: 45667 | C13: C9999 | D13: P075 | E13: 1
... A1001: O01000 | B1001: 45860 | C1001: C0231 | D1001: P040 | E1001: 2

Sheet Pivot Table 1
A3: Row Labels | B3: Sum of Selling Price
A4: Laptop | B4: 7500000
A5: Mobile | B5: 3850000
A6: Monitor | B6: 1536000
A7: Printer | B7: 1245000
A8: Tablet | B8: 1116000
A9: Speaker | B9: 360000
A10: Keyboard | B10: 232500
A11: Mouse | B11: 118400
A12: Grand Total | B12: 15957900

Sheet Pivot Table 2
A3: Row Labels | B3: Sum of Profit
A4: Mouse | B4: 132300
A5: Keyboard | B5: 287400
A6: Speaker | B6: 375000
A7: Tablet | B7: 519000
A8: Printer | B8: 720000
A9: Monitor | B9: 1257000
A10: Mobile | B10: 2275000
A11: Laptop | B11: 3592000
A12: Grand Total | B12: 9157700

Sheet Pivot Table 3
A3: Row Labels | B3: Sum of Gross Sales
A4: Jaipur | B4: 7768800
A5: Lucknow | B5: 7753800
A6: Ahmedabad | B6: 6942400
A7: Mumbai | B7: 4979100
A8: Chandigarh | B8: 4261800
B9: 4249600
A10: Pune | B10: 4063500
A11: Delhi | B11: 3956300
A12: Noida | B12: 3788000
A13: Grand Total | B13: 47763300

Sheet Pivot Table 4
A3: Row Labels | B3: Sum of Gross Sales
A4: Jan | B4: 4719300
A5: Feb | B5: 3330300
A6: Mar | B6: 3274600
A7: Apr | B7: 3407900
A8: May | B8: 5037200
A9: Jun | B9: 3957500
A10: Jul | B10: 3903600
A11: Aug | B11: 4015100
A12: Sep | B12: 2832900
A13: Oct | B13: 3970900
A14: Nov | B14: 4349900
A15: Dec | B15: 4964100
A16: Grand Total | B16: 47763300

Sheet Pivot Table 5
A3: Row Labels | B3: Sum of Profit
A4: Jan | B4: 881200
A5: Feb | B5: 630900
A6: Mar | B6: 629800
A7: Apr | B7: 670100
A8: May | B8: 943200
A9: Jun | B9: 760300
A10: Jul | B10: 764300
A11: Aug | B11: 741800
A12: Sep | B12: 558800
A13: Oct | B13: 775800
A14: Nov | B14: 844200
A15: Dec | B15: 957300
A16: Grand Total | B16: 9157700

Sheet Pivot Table 6
A3: Row Labels | B3: Sum of Gross Sales
A4: Riya Sharma | B4: 6244000
A5: Sneha Roy | B5: 4644400
A6: Karan Patel | B6: 4528300
A7: Arjun Mehta | B7: 4357500
A8: Rahul Sharma | B8: 4081800
A9: Amit Kumar | B9: 3788100
A10: Vikas Yadav | B10: 3649800
A11: Meena Joshi | B11: 3644900
A12: Anjali Gupta | B12: 3339200
A13: Neha Singh | B13: 2756400
A14: Grand Total | B14: 41034400

Sheet Sheet7
A3: Row Labels | B3: Sum of Profit
A4: Accessories | B4: 2051700
A5: Electronics | B5: 7106000
A6: Grand Total | B6: 9157700

Sheet Clean_Data
A1: Order ID | B1: Order Date | C1: Month | D1: Customer ID | E1: Product ID | F1: Quantity | G1: Customer name | H1: City | I1: Product name | J1: Category | K1: Cost Price | L1: Selling Price | M1: Gross Sales | N1: Total Cost | O1: Profit | P1: Profit % | Q1: Profit Category
A2: O00001 | B2: 45748 | C2: =TEXT(B2,"MMMM") -> April | D2: C0020 | E2: P090 | F2: 2 | G2: Riya Sharma | H2: Lucknow | I2: Printer | J2: =_xlfn.XLOOKUP(E2, Product_Master!$A$2:$A$101, Product_Master!$C$2:$C$101) -> Electronics | K2: =_xlfn.XLOOKUP(E2, Product_Master!$A$2:$A$101, Product_Master!$D$2:$D$101) -> 12000 | L2: =_xlfn.XLOOKUP(E2, Product_Master!$A$2:$A$101, Product_Master!$E$2:$E$101) -> 15000 | M2: =F2*L2 -> 30000 | N2: =F2*K2 -> 24000 | O2: =M2-N2 -> 6000 | P2: =O2/M2 -> 0.2 | Q2: {=_xlfn.IFS(P2:P1001>=25%, "High Profit", P2:P1001>=10%, "Low Profit")} -> Low Profit
A3: O00002 | B3: 46015 | C3: =TEXT(B3,"MMMM") -> December | D3: C0142 | E3: P035 | F3: 4 | G3: Karan Patel | H3: Jaipur | I3: Monitor | J3: =_xlfn.XLOOKUP(E3, Product_Master!$A$2:$A$101, Product_Master!$C$2:$C$101) -> Accessories | K3: =_xlfn.XLOOKUP(E3, Product_Master!$A$2:$A$101, Product_Master!$D$2:$D$101) -> 9000 | L3: =_xlfn.XLOOKUP(E3, Product_Master!$A$2:$A$101, Product_Master!$E$2:$E$101) -> 12000 | M3: =F3*L3 -> 48000 | N3: =F3*K3 -> 36000 | O3: =M3-N3 -> 12000 | P3: =O3/M3 -> 0.25 | Q3: High Profit
A4: O00003 | B4: 45668 | C4: =TEXT(B4,"MMMM") -> January | D4: C0300 | E4: P072 | F4: 2 | G4: Rahul Sharma | H4: Pune | I4: Mobile | J4: =_xlfn.XLOOKUP(E4, Product_Master!$A$2:$A$101, Product_Master!$C$2:$C$101) -> Electronics | K4: =_xlfn.XLOOKUP(E4, Product_Master!$A$2:$A$101, Product_Master!$D$2:$D$101) -> 20000 | L4: =_xlfn.XLOOKUP(E4, Product_Master!$A$2:$A$101, Product_Master!$E$2:$E$101) -> 25000 | M4: =F4*L4 -> 50000 | N4: =F4*K4 -> 40000 | O4: =M4-N4 -> 10000 | P4: =O4/M4 -> 0.2 | Q4: Low Profit
A5: O00004 | B5: 45846 | C5: =TEXT(B5,"MMMM") -> July | D5: C0069 | E5: P018 | F5: 5 | G5: Mohan Das | H5: Ahmedabad | I5: Laptop | J5: =_xlfn.XLOOKUP(E5, Product_Master!$A$2:$A$101, Product_Master!$C$2:$C$101) -> Electronics | K5: =_xlfn.XLOOKUP(E5, Product_Master!$A$2:$A$101, Product_Master!$D$2:$D$101) -> 42000 | L5: =_xlfn.XLOOKUP(E5, Product_Master!$A$2:$A$101, Product_Master!$E$2:$E$101) -> 50000 | M5: =F5*L5 -> 250000 | N5: =F5*K5 -> 210000 | O5: =M5-N5 -> 40000 | P5: =O5/M5 -> 0.16 | Q5: Low Profit
A6: O00005 | B6: 45960 | C6: =TEXT(B6,"MMMM") -> October | D6: C0130 | E6: P058 | F6: 2 | G6: Rahul Sharma | H6: Delhi | I6: Keyboard | J6: =_xlfn.XLOOKUP(E6, Product_Master!$A$2:$A$101, Product_Master!$C$2:$C$101) -> Accessories | K6: =_xlfn.XLOOKUP(E6, Product_Master!$A$2:$A$101, Product_Master!$D$2:$D$101) -> 900 | L6: =_xlfn.XLOOKUP(E6, Product_Master!$A$2:$A$101, Product_Master!$E$2:$E$101) -> 1500 | M6: =F6*L6 -> 3000 | N6: =F6*K6 -> 1800 | O6: =M6-N6 -> 1200 | P6: =O6/M6 -> 0.4 | Q6: High Profit
A7: O00006 | B7: 45796 | C7: =TEXT(B7,"MMMM") -> May | D7: C0282 | E7: P042 | F7: 1 | G7: Karan Patel | H7: Mumbai | I7: Keyboard | J7: =_xlfn.XLOOKUP(E7, Product_Master!$A$2:$A$101, Product_Master!$C$2:$C$101) -> Accessories | K7: =_xlfn.XLOOKUP(E7, Product_Master!$A$2:$A$101, Product_Master!$D$2:$D$101) -> 900 | L7: =_xlfn.XLOOKUP(E7, Product_Master!$A$2:$A$101, Product_Master!$E$2:$E$101) -> 1500 | M7: =F7*L7 -> 1500 | N7: =F7*K7 -> 900 | O7: =M7-N7 -> 600 | P7: =O7/M7 -> 0.4 | Q7: High Profit
A8: O00007 | B8: 45913 | C8: =TEXT(B8,"MMMM") -> September | D8: C0031 | E8: P016 | F8: 3 | G8: Arjun Mehta | H8: Chandigarh | I8: Mobile | J8: =_xlfn.XLOOKUP(E8, Product_Master!$A$2:$A$101, Product_Master!$C$2:$C$101) -> Electronics | K8: =_xlfn.XLOOKUP(E8, Product_Master!$A$2:$A$101, Product_Master!$D$2:$D$101) -> 20000 | L8: =_xlfn.XLOOKUP(E8, Product_Master!$A$2:$A$101, Product_Master!$E$2:$E$101) -> 25000 | M8: =F8*L8 -> 75000 | N8: =F8*K8 -> 60000 | O8: =M8-N8 -> 15000 | P8: =O8/M8 -> 0.2 | Q8: Low Profit
A9: O00008 | B9: 45895 | C9: =TEXT(B9,"MMMM") -> August | D9: C0157 | E9: P024 | F9: 1 | G9: Riya Sharma | H9: Ahmedabad | I9: Mouse | J9: =_xlfn.XLOOKUP(E9, Product_Master!$A$2:$A$101, Product_Master!$C$2:$C$101) -> Accessories | K9: =_xlfn.XLOOKUP(E9, Product_Master!$A$2:$A$101, Product_Master!$D$2:$D$101) -> 500 | L9: =_xlfn.XLOOKUP(E9, Product_Master!$A$2:$A$101, Product_Master!$E$2:$E$101) -> 800 | M9: =F9*L9 -> 800 | N9: =F9*K9 -> 500 | O9: =M9-N9 -> 300 | P9: =O9/M9 -> 0.375 | Q9: High Profit
A10: O00009 | B10: 45866 | C10: =TEXT(B10,"MMMM") -> July | D10: C0114 | E10: P027 | F10: 4 | G10: Riya Sharma | H10: Jaipur | I10: Laptop | J10: =_xlfn.XLOOKUP(E10, Product_Master!$A$2:$A$101, Product_Master!$C$2:$C$101) -> Electronics | K10: =_xlfn.XLOOKUP(E10, Product_Master!$A$2:$A$101, Product_Master!$D$2:$D$101) -> 42000 | L10: =_xlfn.XLOOKUP(E10, Product_Master!$A$2:$A$101, Product_Master!$E$2:$E$101) -> 50000 | M10: =F10*L10 -> 200000 | N10: =F10*K10 -> 168000 | O10: =M10-N10 -> 32000 | P10: =O10/M10 -> 0.16 | Q10: Low Profit
A11: O00010 | B11: 45853 | C11: =TEXT(B11,"MMMM") -> July | D11: C0218 | E11: P035 | F11: 5 | G11: Priya Verma | H11: Noida | I11: Monitor | J11: =_xlfn.XLOOKUP(E11, Product_Master!$A$2:$A$101, Product_Master!$C$2:$C$101) -> Accessories | K11: =_xlfn.XLOOKUP(E11, Product_Master!$A$2:$A$101, Product_Master!$D$2:$D$101) -> 9000 | L11: =_xlfn.XLOOKUP(E11, Product_Master!$A$2:$A$101, Product_Master!$E$2:$E$101) -> 12000 | M11: =F11*L11 -> 60000 | N11: =F11*K11 -> 45000 | O11: =M11-N11 -> 15000 | P11: =O11/M11 -> 0.25 | Q11: High Profit
A12: O00011 | B12: 45758 | C12: =TEXT(B12,"MMMM") -> April | D12: C0063 | E12: P032 | F12: 4 | G12: Vikas Yadav | H12: Lucknow | I12: Mobile | J12: =_xlfn.XLOOKUP(E12, Product_Master!$A$2:$A$101, Product_Master!$C$2:$C$101) -> Electronics | K12: =_xlfn.XLOOKUP(E12, Product_Master!$A$2:$A$101, Product_Master!$D$2:$D$101) -> 20000 | L12: =_xlfn.XLOOKUP(E12, Product_Master!$A$2:$A$101, Product_Master!$E$2:$E$101) -> 25000 | M12: =F12*L12 -> 100000 | N12: =F12*K12 -> 80000 | O12: =M12-N12 -> 20000 | P12: =O12/M12 -> 0.2 | Q12: Low Profit
A13: O00012 | B13: 45667 | C13: =TEXT(B13,"MMMM") -> January | D13: C9999 | E13: P075 | F13: 1 | G13: Invailid | I13: Mobile | J13: =_xlfn.XLOOKUP(E13, Product_Master!$A$2:$A$101, Product_Master!$C$2:$C$101) -> Electronics | K13: =_xlfn.XLOOKUP(E13, Product_Master!$A$2:$A$101, Product_Master!$D$2:$D$101) -> 20000 | L13: =_xlfn.XLOOKUP(E13, Product_Master!$A$2:$A$101, Product_Master!$E$2:$E$101) -> 25000 | M13: =F13*L13 -> 25000 | N13: =F13*K13 -> 20000 | O13: =M13-N13 -> 5000 | P13: =O13/M13 -> 0.2 | Q13: Low Profit
A14: O00013 | B14: 45937 | C14: =TEXT(B14,"MMMM") -> October | D14: C0162 | E14: P005 | F14: 2 | G14: Riya Sharma | H14: Noida | I14: Mouse | J14: =_xlfn.XLOOKUP(E14, Product_Master!$A$2:$A$101, Product_Master!$C$2:$C$101) -> Accessories | K14: =_xlfn.XLOOKUP(E14, Product_Master!$A$2:$A$101, Product_Master!$D$2:$D$101) -> 500 | L14: =_xlfn.XLOOKUP(E14, Product_Master!$A$2:$A$101, Product_Master!$E$2:$E$101) -> 800 | M14: =F14*L14 -> 1600 | N14: =F14*K14 -> 1000 | O14: =M14-N14 -> 600 | P14: =O14/M14 -> 0.375 | Q14: High Profit
A15: O00014 | B15: 46003 | C15: =TEXT(B15,"MMMM") -> December | D15: C0172 | E15: P014 | F15: 1 | G15: Priya Verma | H15: Delhi | I15: Mouse | J15: =_xlfn.XLOOKUP(E15, Product_Master!$A$2:$A$101, Product_Master!$C$2:$C$101) -> Accessories | K15: =_xlfn.XLOOKUP(E15, Product_Master!$A$2:$A$101, Product_Master!$D$2:$D$101) -> 500 | L15: =_xlfn.XLOOKUP(E15, Product_Master!$A$2:$A$101, Product_Master!$E$2:$E$101) -> 800 | M15: =F15*L15 -> 800 | N15: =F15*K15 -> 500 | O15: =M15-N15 -> 300 | P15: =O15/M15 -> 0.375 | Q15: High Profit
A16: O00015 | B16: 45962 | C16: =TEXT(B16,"MMMM") -> November | D16: C0077 | E16: P043 | F16: 3 | G16: Karan Patel | H16: Noida | I16: Printer | J16: =_xlfn.XLOOKUP(E16, Product_Master!$A$2:$A$101, Product_Master!$C$2:$C$101) -> Electronics | K16: =_xlfn.XLOOKUP(E16, Product_Master!$A$2:$A$101, Product_Master!$D$2:$D$101) -> 12000 | L16: =_xlfn.XLOOKUP(E16, Product_Master!$A$2:$A$101, Product_Master!$E$2:$E$101) -> 15000 | M16: =F16*L16 -> 45000 | N16: =F16*K16 -> 36000 | O16: =M16-N16 -> 9000 | P16: =O16/M16 -> 0.2 | Q16: Low Profit
A17: O00016 | B17: 45767 | C17: =TEXT(B17,"MMMM") -> April | D17: C0164 | E17: P091 | F17: 1 | G17: Arjun Mehta | H17: Pune | I17: Monitor | J17: =_xlfn.XLOOKUP(E17, Product_Master!$A$2:$A$101, Product_Master!$C$2:$C$101) -> Accessories | K17: =_xlfn.XLOOKUP(E17, Product_Master!$A$2:$A$101, Product_Master!$D$2:$D$101) -> 9000 | L17: =_xlfn.XLOOKUP(E17, Product_Master!$A$2:$A$101, Product_Master!$E$2:$E$101) -> 12000 | M17: =F17*L17 -> 12000 | N17: =F17*K17 -> 9000 | O17: =M17-N17 -> 3000 | P17: =O17/M17 -> 0.25 | Q17: High Profit
A18: O00017 | B18: 45971 | C18: =TEXT(B18,"MMMM") -> November | D18: C0259 | E18: P085 | F18: 3 | G18: Priya Verma | H18: Jaipur | I18: Keyboard | J18: =_xlfn.XLOOKUP(E18, Product_Master!$A$2:$A$101, Product_Master!$C$2:$C$101) -> Accessories | K18: =_xlfn.XLOOKUP(E18, Product_Master!$A$2:$A$101, Product_Master!$D$2:$D$101) -> 900 | L18: =_xlfn.XLOOKUP(E18, Product_Master!$A$2:$A$101, Product_Master!$E$2:$E$101) -> 1500 | M18: =F18*L18 -> 4500 | N18: =F18*K18 -> 2700 | O18: =M18-N18 -> 1800 | P18: =O18/M18 -> 0.4 | Q18: High Profit
A19: O00018 | B19: 45895 | C19: =TEXT(B19,"MMMM") -> August | D19: C0287 | E19: P100 | F19: 3 | G19: Riya Sharma | H19: Noida | I19: Speaker | J19: =_xlfn.XLOOKUP(E19, Product_Master!$A$2:$A$101, Product_Master!$C$2:$C$101) -> Accessories | K19: =_xlfn.XLOOKUP(E19, Product_Master!$A$2:$A$101, Product_Master!$D$2:$D$101) -> 2000 | L19: =_xlfn.XLOOKUP(E19, Product_Master!$A$2:$A$101, Product_Master!$E$2:$E$101) -> 3000 | M19: =F19*L19 -> 9000 | N19: =F19*K19 -> 6000 | O19: =M19-N19 -> 3000 | P19: =O19/M19 -> 0.33333333 | Q19: High Profit
A20: O00019 | B20: 45857 | C20: =TEXT(B20,"MMMM") -> July | D20: C0077 | E20: P044 | F20: 3 | G20: Karan Patel | H20: Noida | I20: Laptop | J20: =_xlfn.XLOOKUP(E20, Product_Master!$A$2:$A$101, Product_Master!$C$2:$C$101) -> Electronics | K20: =_xlfn.XLOOKUP(E20, Product_Master!$A$2:$A$101, Product_Master!$D$2:$D$101) -> 42000 | L20: =_xlfn.XLOOKUP(E20, Product_Master!$A$2:$A$101, Product_Master!$E$2:$E$101) -> 50000 | M20: =F20*L20 -> 150000 | N20: =F20*K20 -> 126000 | O20: =M20-N20 -> 24000 | P20: =O20/M20 -> 0.16 | Q20: Low Profit
A21: O00020 | B21: 45693 | C21: =TEXT(B21,"MMMM") -> February | D21: C0219 | E21: P010 | F21: 3 | G21: Riya Sharma | H21: Lucknow | I21: Monitor | J21: =_xlfn.XLOOKUP(E21, Product_Master!$A$2:$A$101, Product_Master!$C$2:$C$101) -> Accessories | K21: =_xlfn.XLOOKUP(E21, Product_Master!$A$2:$A$101, Product_Master!$D$2:$D$101) -> 9000 | L21: =_xlfn.XLOOKUP(E21, Product_Master!$A$2:$A$101, Product_Master!$E$2:$E$101) -> 12000 | M21: =F21*L21 -> 36000 | N21: =F21*K21 -> 27000 | O21: =M21-N21 -> 9000 | P21: =O21/M21 -> 0.25 | Q21: High Profit
A22: O00021 | B22: 45969 | C22: =TEXT(B22,"MMMM") -> November | D22: C8888 | E22: P001 | F22: 5 | G22: Invailid | I22: Mobile | J22: =_xlfn.XLOOKUP(E22, Product_Master!$A$2:$A$101, Product_Master!$C$2:$C$101) -> Electronics | K22: =_xlfn.XLOOKUP(E22, Product_Master!$A$2:$A$101, Product_Master!$D$2:$D$101) -> 20000 | L22: =_xlfn.XLOOKUP(E22, Product_Master!$A$2:$A$101, Product_Master!$E$2:$E$101) -> 25000 | M22: =F22*L22 -> 125000 | N22: =F22*K22 -> 100000 | O22: =M22-N22 -> 25000 | P22: =O22/M22 -> 0.2 | Q22: Low Profit
A23: O00022 | B23: 45809 | C23: =TEXT(B23,"MMMM") -> June | D23: C0197 | E23: P024 | F23: 5 | G23: Arjun Mehta | H23: Jaipur | I23: Mouse | J23: =_xlfn.XLOOKUP(E23, Product_Master!$A$2:$A$101, Product_Master!$C$2:$C$101) -> Accessories | K23: =_xlfn.XLOOKUP(E23, Product_Master!$A$2:$A$101, Product_Master!$D$2:$D$101) -> 500 | L23: =_xlfn.XLOOKUP(E23, Product_Master!$A$2:$A$101, Product_Master!$E$2:$E$101) -> 800 | M23: =F23*L23 -> 4000 | N23: =F23*K23 -> 2500 | O23: =M23-N23 -> 1500 | P23: =O23/M23 -> 0.375 | Q23: High Profit
A24: O00023 | B24: 45803 | C24: =TEXT(B24,"MMMM") -> May | D24: C0263 | E24: P081 | F24: 3 | G24: Neha Singh | I24: Tablet | J24: =_xlfn.XLOOKUP(E24, Product_Master!$A$2:$A$101, Product_Master!$C$2:$C$101) -> Electronics | K24: =_xlfn.XLOOKUP(E24, Product_Master!$A$2:$A$101, Product_Master!$D$2:$D$101) -> 15000 | L24: =_xlfn.XLOOKUP(E24, Product_Master!$A$2:$A$101, Product_Master!$E$2:$E$101) -> 18000 | M24: =F24*L24 -> 54000 | N24: =F24*K24 -> 45000 | O24: =M24-N24 -> 9000 | P24: =O24/M24 -> 0.16666667 | Q24: Low Profit
A25: O00024 | B25: 45739 | C25: =TEXT(B25,"MMMM") -> March | D25: C0217 | E25: P026 | F25: 1 | G25: Anjali Gupta | H25: Noida | I25: Monitor | J25: =_xlfn.XLOOKUP(E25, Product_Master!$A$2:$A$101, Product_Master!$C$2:$C$101) -> Accessories | K25: =_xlfn.XLOOKUP(E25, Product_Master!$A$2:$A$101, Product_Master!$D$2:$D$101) -> 9000 | L25: =_xlfn.XLOOKUP(E25, Product_Master!$A$2:$A$101, Product_Master!$E$2:$E$101) -> 12000 | M25: =F25*L25 -> 12000 | N25: =F25*K25 -> 9000 | O25: =M25-N25 -> 3000 | P25: =O25/M25 -> 0.25 | Q25: High Profit
A26: O00025 | B26: 45658 | C26: =TEXT(B26,"MMMM") -> January | D26: C0168 | E26: P048 | F26: 3 | G26: Vikas Yadav | H26: Lucknow | I26: Tablet | J26: =_xlfn.XLOOKUP(E26, Product_Master!$A$2:$A$101, Product_Master!$C$2:$C$101) -> Electronics | K26: =_xlfn.XLOOKUP(E26, Product_Master!$A$2:$A$101, Product_Master!$D$2:$D$101) -> 15000 | L26: =_xlfn.XLOOKUP(E26, Product_Master!$A$2:$A$101, Product_Master!$E$2:$E$101) -> 18000 | M26: =F26*L26 -> 54000 | N26: =F26*K26 -> 45000 | O26: =M26-N26 -> 9000 | P26: =O26/M26 -> 0.16666667 | Q26: Low Profit
A27: O00026 | B27: 45738 | C27: =TEXT(B27,"MMMM") -> March | D27: C0244 | E27: P023 | F27: 5 | G27: Amit Kumar | H27: Mumbai | I27: Speaker | J27: =_xlfn.XLOOKUP(E27, Product_Master!$A$2:$A$101, Product_Master!$C$2:$C$101) -> Accessories | K27: =_xlfn.XLOOKUP(E27, Product_Master!$A$2:$A$101, Product_Master!$D$2:$D$101) -> 2000 | L27: =_xlfn.XLOOKUP(E27, Product_Master!$A$2:$A$101, Product_Master!$E$2:$E$101) -> 3000 | M27: =F27*L27 -> 15000 | N27: =F27*K27 -> 10000 | O27: =M27-N27 -> 5000 | P27: =O27/M27 -> 0.33333333 | Q27: High Profit
A28: O00027 | B28: 45665 | C28: =TEXT(B28,"MMMM") -> January | D28: C0119 | E28: P082 | F28: 1 | G28: Anjali Gupta | H28: Chandigarh | I28: Tablet | J28: =_xlfn.XLOOKUP(E28, Product_Master!$A$2:$A$101, Product_Master!$C$2:$C$101) -> Electronics | K28: =_xlfn.XLOOKUP(E28, Product_Master!$A$2:$A$101, Product_Master!$D$2:$D$101) -> 15000 | L28: =_xlfn.XLOOKUP(E28, Product_Master!$A$2:$A$101, Product_Master!$E$2:$E$101) -> 18000 | M28: =F28*L28 -> 18000 | N28: =F28*K28 -> 15000 | O28: =M28-N28 -> 3000 | P28: =O28/M28 -> 0.16666667 | Q28: Low Profit
A29: O00028 | B29: 45867 | C29: =TEXT(B29,"MMMM") -> July | D29: C0058 | E29: P099 | F29: 4 | G29: Sneha Roy | H29: Ahmedabad | I29: Keyboard | J29: =_xlfn.XLOOKUP(E29, Product_Master!$A$2:$A$101, Product_Master!$C$2:$C$101) -> Accessories | K29: =_xlfn.XLOOKUP(E29, Product_Master!$A$2:$A$101, Product_Master!$D$2:$D$101) -> 900 | L29: =_xlfn.XLOOKUP(E29, Product_Master!$A$2:$A$101, Product_Master!$E$2:$E$101) -> 1500 | M29: =F29*L29 -> 6000 | N29: =F29*K29 -> 3600 | O29: =M29-N29 -> 2400 | P29: =O29/M29 -> 0.4 | Q29: High Profit
A30: O00029 | B30: 45834 | C30: =TEXT(B30,"MMMM") -> June | D30: C0055 | E30: P040 | F30: 1 | G30: Sneha Roy | H30: Chandigarh | I30: Laptop | J30: =_xlfn.XLOOKUP(E30, Product_Master!$A$2:$A$101, Product_Master!$C$2:$C$101) -> Electronics | K30: =_xlfn.XLOOKUP(E30, Product_Master!$A$2:$A$101, Product_Master!$D$2:$D$101) -> 42000 | L30: =_xlfn.XLOOKUP(E30, Product_Master!$A$2:$A$101, Product_Master!$E$2:$E$101) -> 50000 | M30: =F30*L30 -> 50000 | N30: =F30*K30 -> 42000 | O30: =M30-N30 -> 8000 | P30: =O30/M30 -> 0.16 | Q30: Low Profit
A31: O00030 | B31: 45877 | C31: =TEXT(B31,"MMMM") -> August | D31: C0024 | E31: P086 | F31: 3 | G31: Karan Patel | H31: Ahmedabad | I31: Laptop | J31: =_xlfn.XLOOKUP(E31, Product_Master!$A$2:$A$101, Product_Master!$C$2:$C$101) -> Electronics | K31: =_xlfn.XLOOKUP(E31, Product_Master!$A$2:$A$101, Product_Master!$D$2:$D$101) -> 42000 | L31: =_xlfn.XLOOKUP(E31, Product_Master!$A$2:$A$101, Product_Master!$E$2:$E$101) -> 50000 | M31: =F31*L31 -> 150000 | N31: =F31*K31 -> 126000 | O31: =M31-N31 -> 24000 | P31: =O31/M31 -> 0.16 | Q31: Low Profit
A32: O00031 | B32: 45751 | C32: =TEXT(B32,"MMMM") -> April | D32: C0014 | E32: P044 | F32: 4 | G32: Riya Sharma | H32: Jaipur | I32: Laptop | J32: =_xlfn.XLOOKUP(E32, Product_Master!$A$2:$A$101, Product_Master!$C$2:$C$101) -> Electronics | K32: =_xlfn.XLOOKUP(E32, Product_Master!$A$2:$A$101, Product_Master!$D$2:$D$101) -> 42000 | L32: =_xlfn.XLOOKUP(E32, Product_Master!$A$2:$A$101, Product_Master!$E$2:$E$101) -> 50000 | M32: =F32*L32 -> 200000 | N32: =F32*K32 -> 168000 | O32: =M32-N32 -> 32000 | P32: =O32/M32 -> 0.16 | Q32: Low Profit
A33: O00032 | B33: 45724 | C33: =TEXT(B33,"MMMM") -> March | D33: C0103 | E33: P060 | F33: 5 | G33: Mohan Das | H33: Mumbai | I33: Mouse | J33: =_xlfn.XLOOKUP(E33, Product_Master!$A$2:$A$101, Product_Master!$C$2:$C$101) -> Accessories | K33: =_xlfn.XLOOKUP(E33, Product_Master!$A$2:$A$101, Product_Master!$D$2:$D$101) -> 500 | L33: =_xlfn.XLOOKUP(E33, Product_Master!$A$2:$A$101, Product_Master!$E$2:$E$101) -> 800 | M33: =F33*L33 -> 4000 | N33: =F33*K33 -> 2500 | O33: =M33-N33 -> 1500 | P33: =O33/M33 -> 0.375 | Q33: High Profit
A34: O00033 | B34: 45847 | C34: =TEXT(B34,"MMMM") -> July | D34: C0294 | E34: P088 | F34: 3 | G34: Mohan Das | H34: Chandigarh | I34: Mouse | J34: =_xlfn.XLOOKUP(E34, Product_Master!$A$2:$A$101, Product_Master!$C$2:$C$101) -> Accessories | K34: =_xlfn.XLOOKUP(E34, Product_Master!$A$2:$A$101, Product_Master!$D$2:$D$101) -> 500 | L34: =_xlfn.XLOOKUP(E34, Product_Master!$A$2:$A$101, Product_Master!$E$2:$E$101) -> 800 | M34: =F34*L34 -> 2400 | N34: =F34*K34 -> 1500 | O34: =M34-N34 -> 900 | P34: =O34/M34 -> 0.375 | Q34: High Profit
A35: O00034 | B35: 45765 | C35: =TEXT(B35,"MMMM") -> April | D35: C0182 | E35: P016 | F35: 4 | G35: Amit Kumar | H35: Ahmedabad | I35: Mobile | J35: =_xlfn.XLOOKUP(E35, Product_Master!$A$2:$A$101, Product_Master!$C$2:$C$101) -> Electronics | K35: =_xlfn.XLOOKUP(E35, Product_Master!$A$2:$A$101, Product_Master!$D$2:$D$101) -> 20000 | L35: =_xlfn.XLOOKUP(E35, Product_Master!$A$2:$A$101, Product_Master!$E$2:$E$101) -> 25000 | M35: =F35*L35 -> 100000 | N35: =F35*K35 -> 80000 | O35: =M35-N35 -> 20000 | P35: =O35/M35 -> 0.2 | Q35: Low Profit
A36: O00035 | B36: 45918 | C36: =TEXT(B36,"MMMM") -> September | D36: C0280 | E36: P075 | F36: 2 | G36: Amit Kumar | H36: Pune | I36: Mobile | J36: =_xlfn.XLOOKUP(E36, Product_Master!$A$2:$A$101, Product_Master!$C$2:$C$101) -> Electronics | K36: =_xlfn.XLOOKUP(E36, Product_Master!$A$2:$A$101, Product_Master!$D$2:$D$101) -> 20000 | L36: =_xlfn.XLOOKUP(E36, Product_Master!$A$2:$A$101, Product_Master!$E$2:$E$101) -> 25000 | M36: =F36*L36 -> 50000 | N36: =F36*K36 -> 40000 | O36: =M36-N36 -> 10000 | P36: =O36/M36 -> 0.2 | Q36: Low Profit
... A66: O00065 | B66: 45854 | C66: =TEXT(B66,"MMMM") -> July | D66: C0248 | E66: P057 | F66: 5 | G66: Amit Kumar | H66: Delhi | I66: Laptop | J66: =_xlfn.XLOOKUP(E66, Product_Master!$A$2:$A$101, Product_Master!$C$2:$C$101) -> Electronics | K66: =_xlfn.XLOOKUP(E66, Product_Master!$A$2:$A$101, Product_Master!$D$2:$D$101) -> 42000 | L66: =_xlfn.XLOOKUP(E66, Product_Master!$A$2:$A$101, Product_Master!$E$2:$E$101) -> 50000 | M66: =F66*L66 -> 250000 | N66: =F66*K66 -> 210000 | O66: =M66-N66 -> 40000 | P66: =O66/M66 -> 0.16 | Q66: Low Profit
A67: O00066 | B67: 45799 | C67: =TEXT(B67,"MMMM") -> May | D67: C8888 | E67: P057 | F67: 1 | G67: Invailid | I67: Laptop | J67: =_xlfn.XLOOKUP(E67, Product_Master!$A$2:$A$101, Product_Master!$C$2:$C$101) -> Electronics | K67: =_xlfn.XLOOKUP(E67, Product_Master!$A$2:$A$101, Product_Master!$D$2:$D$101) -> 42000 | L67: =_xlfn.XLOOKUP(E67, Product_Master!$A$2:$A$101, Product_Master!$E$2:$E$101) -> 50000 | M67: =F67*L67 -> 50000 | N67: =F67*K67 -> 42000 | O67: =M67-N67 -> 8000 | P67: =O67/M67 -> 0.16 | Q67: Low Profit
A68: O00067 | B68: 45971 | C68: =TEXT(B68,"MMMM") -> November | D68: C0075 | E68: P090 | F68: 2 | G68: Mohan Das | H68: Jaipur | I68: Printer | J68: =_xlfn.XLOOKUP(E68, Product_Master!$A$2:$A$101, Product_Master!$C$2:$C$101) -> Electronics | K68: =_xlfn.XLOOKUP(E68, Product_Master!$A$2:$A$101, Product_Master!$D$2:$D$101) -> 12000 | L68: =_xlfn.XLOOKUP(E68, Product_Master!$A$2:$A$101, Product_Master!$E$2:$E$101) -> 15000 | M68: =F68*L68 -> 30000 | N68: =F68*K68 -> 24000 | O68: =M68-N68 -> 6000 | P68: =O68/M68 -> 0.2 | Q68: Low Profit
A69: O00068 | B69: 45688 | C69: =TEXT(B69,"MMMM") -> January | D69: C0108 | E69: P002 | F69: 1 | G69: Priya Verma | H69: Lucknow | I69: Mouse | J69: =_xlfn.XLOOKUP(E69, Product_Master!$A$2:$A$101, Product_Master!$C$2:$C$101) -> Accessories | K69: =_xlfn.XLOOKUP(E69, Product_Master!$A$2:$A$101, Product_Master!$D$2:$D$101) -> 500 | L69: =_xlfn.XLOOKUP(E69, Product_Master!$A$2:$A$101, Product_Master!$E$2:$E$101) -> 800 | M69: =F69*L69 -> 800 | N69: =F69*K69 -> 500 | O69: =M69-N69 -> 300 | P69: =O69/M69 -> 0.375 | Q69: High Profit
A70: O00069 | B70: 46013 | C70: =TEXT(B70,"MMMM") -> December | D70: C0275 | E70: P023 | F70: 2 | G70: Arjun Mehta | I70: Speaker | J70: =_xlfn.XLOOKUP(E70, Product_Master!$A$2:$A$101, Product_Master!$C$2:$C$101) -> Accessories | K70: =_xlfn.XLOOKUP(E70, Product_Master!$A$2:$A$101, Product_Master!$D$2:$D$101) -> 2000 | L70: =_xlfn.XLOOKUP(E70, Product_Master!$A$2:$A$101, Product_Master!$E$2:$E$101) -> 3000 | M70: =F70*L70 -> 6000 | N70: =F70*K70 -> 4000 | O70: =M70-N70 -> 2000 | P70: =O70/M70 -> 0.33333333 | Q70: High Profit
A71: O00070 | B71: 45951 | C71: =TEXT(B71,"MMMM") -> October | D71: C0248 | E71: P019 | F71: 1 | G71: Amit Kumar | H71: Delhi | I71: Laptop | J71: =_xlfn.XLOOKUP(E71, Product_Master!$A$2:$A$101, Product_Master!$C$2:$C$101) -> Electronics | K71: =_xlfn.XLOOKUP(E71, Product_Master!$A$2:$A$101, Product_Master!$D$2:$D$101) -> 42000 | L71: =_xlfn.XLOOKUP(E71, Product_Master!$A$2:$A$101, Product_Master!$E$2:$E$101) -> 50000 | M71: =F71*L71 -> 50000 | N71: =F71*K71 -> 42000 | O71: =M71-N71 -> 8000 | P71: =O71/M71 -> 0.16 | Q71: Low Profit
A72: O00071 | B72: 45692 | C72: =TEXT(B72,"MMMM") -> February | D72: C0036 | E72: P041 | F72: 4 | G72: Karan Patel | H72: Jaipur | I72: Mobile | J72: =_xlfn.XLOOKUP(E72, Product_Master!$A$2:$A$101, Product_Master!$C$2:$C$101) -> Electronics | K72: =_xlfn.XLOOKUP(E72, Product_Master!$A$2:$A$101, Product_Master!$D$2:$D$101) -> 20000 | L72: =_xlfn.XLOOKUP(E72, Product_Master!$A$2:$A$101, Product_Master!$E$2:$E$101) -> 25000 | M72: =F72*L72 -> 100000 | N72: =F72*K72 -> 80000 | O72: =M72-N72 -> 20000 | P72: =O72/M72 -> 0.2 | Q72: Low Profit
A73: O00072 | B73: 45713 | C73: =TEXT(B73,"MMMM") -> February | D73: C0179 | E73: P051 | F73: 3 | G73: Arjun Mehta | H73: Ahmedabad | I73: Speaker | J73: =_xlfn.XLOOKUP(E73, Product_Master!$A$2:$A$101, Product_Master!$C$2:$C$101) -> Accessories | K73: =_xlfn.XLOOKUP(E73, Product_Master!$A$2:$A$101, Product_Master!$D$2:$D$101) -> 2000 | L73: =_xlfn.XLOOKUP(E73, Product_Master!$A$2:$A$101, Product_Master!$E$2:$E$101) -> 3000 | M73: =F73*L73 -> 9000 | N73: =F73*K73 -> 6000 | O73: =M73-N73 -> 3000 | P73: =O73/M73 -> 0.33333333 | Q73: High Profit
A74: O00073 | B74: 45972 | C74: =TEXT(B74,"MMMM") -> November | D74: C0018 | E74: P052 | F74: 4 | G74: Sneha Roy | H74: Mumbai | I74: Mouse | J74: =_xlfn.XLOOKUP(E74, Product_Master!$A$2:$A$101, Product_Master!$C$2:$C$101) -> Accessories | K74: =_xlfn.XLOOKUP(E74, Product_Master!$A$2:$A$101, Product_Master!$D$2:$D$101) -> 500 | L74: =_xlfn.XLOOKUP(E74, Product_Master!$A$2:$A$101, Product_Master!$E$2:$E$101) -> 800 | M74: =F74*L74 -> 3200 | N74: =F74*K74 -> 2000 | O74: =M74-N74 -> 1200 | P74: =O74/M74 -> 0.375 | Q74: High Profit
A75: O00074 | B75: 45784 | C75: =TEXT(B75,"MMMM") -> May | D75: C0125 | E75: P032 | F75: 2 | G75: Meena Joshi | H75: Lucknow | I75: Mobile | J75: =_xlfn.XLOOKUP(E75, Product_Master!$A$2:$A$101, Product_Master!$C$2:$C$101) -> Electronics | K75: =_xlfn.XLOOKUP(E75, Product_Master!$A$2:$A$101, Product_Master!$D$2:$D$101) -> 20000 | L75: =_xlfn.XLOOKUP(E75, Product_Master!$A$2:$A$101, Product_Master!$E$2:$E$101) -> 25000 | M75: =F75*L75 -> 50000 | N75: =F75*K75 -> 40000 | O75: =M75-N75 -> 10000 | P75: =O75/M75 -> 0.2 | Q75: Low Profit
A76: O00075 | B76: 45802 | C76: =TEXT(B76,"MMMM") -> May | D76: C0142 | E76: P007 | F76: 2 | G76: Karan Patel | H76: Jaipur | I76: Mobile | J76: =_xlfn.XLOOKUP(E76, Product_Master!$A$2:$A$101, Product_Master!$C$2:$C$101) -> Electronics | K76: =_xlfn.XLOOKUP(E76, Product_Master!$A$2:$A$101, Product_Master!$D$2:$D$101) -> 20000 | L76: =_xlfn.XLOOKUP(E76, Product_Master!$A$2:$A$101, Product_Master!$E$2:$E$101) -> 25000 | M76: =F76*L76 -> 50000 | N76: =F76*K76 -> 40000 | O76: =M76-N76 -> 10000 | P76: =O76/M76 -> 0.2 | Q76: Low Profit
A77: O00076 | B77: 45748 | C77: =TEXT(B77,"MMMM") -> April | D77: C0121 | E77: P025 | F77: 3 | G77: Riya Sharma | H77: Lucknow | I77: Monitor | J77: =_xlfn.XLOOKUP(E77, Product_Master!$A$2:$A$101, Product_Master!$C$2:$C$101) -> Accessories | K77: =_xlfn.XLOOKUP(E77, Product_Master!$A$2:$A$101, Product_Master!$D$2:$D$101) -> 9000 | L77: =_xlfn.XLOOKUP(E77, Product_Master!$A$2:$A$101, Product_Master!$E$2:$E$101) -> 12000 | M77: =F77*L77 -> 36000 | N77: =F77*K77 -> 27000 | O77: =M77-N77 -> 9000 | P77: =O77/M77 -> 0.25 | Q77: High Profit
A78: O00077 | B78: 45736 | C78: =TEXT(B78,"MMMM") -> March | D78: C0084 | E78: P012 | F78: 1 | G78: Karan Patel | H78: Chandigarh | I78: Keyboard | J78: =_xlfn.XLOOKUP(E78, Product_Master!$A$2:$A$101, Product_Master!$C$2:$C$101) -> Accessories | K78: =_xlfn.XLOOKUP(E78, Product_Master!$A$2:$A$101, Product_Master!$D$2:$D$101) -> 900 | L78: =_xlfn.XLOOKUP(E78, Product_Master!$A$2:$A$101, Product_Master!$E$2:$E$101) -> 1500 | M78: =F78*L78 -> 1500 | N78: =F78*K78 -> 900 | O78: =M78-N78 -> 600 | P78: =O78/M78 -> 0.4 | Q78: High Profit
A79: O00078 | B79: 45806 | C79: =TEXT(B79,"MMMM") -> May | D79: C0198 | E79: P017 | F79: 4 | G79: Meena Joshi | H79: Ahmedabad | I79: Keyboard | J79: =_xlfn.XLOOKUP(E79, Product_Master!$A$2:$A$101, Product_Master!$C$2:$C$101) -> Accessories | K79: =_xlfn.XLOOKUP(E79, Product_Master!$A$2:$A$101, Product_Master!$D$2:$D$101) -> 900 | L79: =_xlfn.XLOOKUP(E79, Product_Master!$A$2:$A$101, Product_Master!$E$2:$E$101) -> 1500 | M79: =F79*L79 -> 6000 | N79: =F79*K79 -> 3600 | O79: =M79-N79 -> 2400 | P79: =O79/M79 -> 0.4 | Q79: High Profit
A80: O00079 | B80: 45862 | C80: =TEXT(B80,"MMMM") -> July | D80: C0134 | E80: P024 | F80: 5 | G80: Riya Sharma | H80: Lucknow | I80: Mouse | J80: =_xlfn.XLOOKUP(E80, Product_Master!$A$2:$A$101, Product_Master!$C$2:$C$101) -> Accessories | K80: =_xlfn.XLOOKUP(E80, Product_Master!$A$2:$A$101, Product_Master!$D$2:$D$101) -> 500 | L80: =_xlfn.XLOOKUP(E80, Product_Master!$A$2:$A$101, Product_Master!$E$2:$E$101) -> 800 | M80: =F80*L80 -> 4000 | N80: =F80*K80 -> 2500 | O80: =M80-N80 -> 1500 | P80: =O80/M80 -> 0.375 | Q80: High Profit
A81: O00080 | B81: 45736 | C81: =TEXT(B81,"MMMM") -> March | D81: C0171 | E81: P082 | F81: 1 | G81: Riya Sharma | H81: Mumbai | I81: Tablet | J81: =_xlfn.XLOOKUP(E81, Product_Master!$A$2:$A$101, Product_Master!$C$2:$C$101) -> Electronics | K81: =_xlfn.XLOOKUP(E81, Product_Master!$A$2:$A$101, Product_Master!$D$2:$D$101) -> 15000 | L81: =_xlfn.XLOOKUP(E81, Product_Master!$A$2:$A$101, Product_Master!$E$2:$E$101) -> 18000 | M81: =F81*L81 -> 18000 | N81: =F81*K81 -> 15000 | O81: =M81-N81 -> 3000 | P81: =O81/M81 -> 0.16666667 | Q81: Low Profit
A82: O00081 | B82: 45937 | C82: =TEXT(B82,"MMMM") -> October | D82: C0092 | E82: P049 | F82: 3 | G82: Mohan Das | H82: Jaipur | I82: Speaker | J82: =_xlfn.XLOOKUP(E82, Product_Master!$A$2:$A$101, Product_Master!$C$2:$C$101) -> Accessories | K82: =_xlfn.XLOOKUP(E82, Product_Master!$A$2:$A$101, Product_Master!$D$2:$D$101) -> 2000 | L82: =_xlfn.XLOOKUP(E82, Product_Master!$A$2:$A$101, Product_Master!$E$2:$E$101) -> 3000 | M82: =F82*L82 -> 9000 | N82: =F82*K82 -> 6000 | O82: =M82-N82 -> 3000 | P82: =O82/M82 -> 0.33333333 | Q82: High Profit
... A88: O00087 | B88: 46004 | C88: =TEXT(B88,"MMMM") -> December | D88: C0234 | E88: P077 | F88: 4 | G88: Sneha Roy | H88: Lucknow | I88: Mobile | J88: =_xlfn.XLOOKUP(E88, Product_Master!$A$2:$A$101, Product_Master!$C$2:$C$101) -> Electronics | K88: =_xlfn.XLOOKUP(E88, Product_Master!$A$2:$A$101, Product_Master!$D$2:$D$101) -> 20000 | L88: =_xlfn.XLOOKUP(E88, Product_Master!$A$2:$A$101, Product_Master!$E$2:$E$101) -> 25000 | M88: =F88*L88 -> 100000 | N88: =F88*K88 -> 80000 | O88: =M88-N88 -> 20000 | P88: =O88/M88 -> 0.2 | Q88: Low Profit
A89: O00088 | B89: 45783 | C89: =TEXT(B89,"MMMM") -> May | D89: C0015 | E89: P087 | F89: 2 | G89: Riya Sharma | I89: Monitor | J89: =_xlfn.XLOOKUP(E89, Product_Master!$A$2:$A$101, Product_Master!$C$2:$C$101) -> Accessories | K89: =_xlfn.XLOOKUP(E89, Product_Master!$A$2:$A$101, Product_Master!$D$2:$D$101) -> 9000 | L89: =_xlfn.XLOOKUP(E89, Product_Master!$A$2:$A$101, Product_Master!$E$2:$E$101) -> 12000 | M89: =F89*L89 -> 24000 | N89: =F89*K89 -> 18000 | O89: =M89-N89 -> 6000 | P89: =O89/M89 -> 0.25 | Q89: High Profit
A90: O00089 | B90: 45764 | C90: =TEXT(B90,"MMMM") -> April | D90: C0105 | E90: P092 | F90: 5 | G90: Sneha Roy | H90: Pune | I90: Monitor | J90: =_xlfn.XLOOKUP(E90, Product_Master!$A$2:$A$101, Product_Master!$C$2:$C$101) -> Accessories | K90: =_xlfn.XLOOKUP(E90, Product_Master!$A$2:$A$101, Product_Master!$D$2:$D$101) -> 9000 | L90: =_xlfn.XLOOKUP(E90, Product_Master!$A$2:$A$101, Product_Master!$E$2:$E$101) -> 12000 | M90: =F90*L90 -> 60000 | N90: =F90*K90 -> 45000 | O90: =M90-N90 -> 15000 | P90: =O90/M90 -> 0.25 | Q90: High Profit
A91: O00090 | B91: 46006 | C91: =TEXT(B91,"MMMM") -> December | D91: C0118 | E91: P075 | F91: 3 | G91: Meena Joshi | H91: Lucknow | I91: Mobile | J91: =_xlfn.XLOOKUP(E91, Product_Master!$A$2:$A$101, Product_Master!$C$2:$C$101) -> Electronics | K91: =_xlfn.XLOOKUP(E91, Product_Master!$A$2:$A$101, Product_Master!$D$2:$D$101) -> 20000 | L91: =_xlfn.XLOOKUP(E91, Product_Master!$A$2:$A$101, Product_Master!$E$2:$E$101) -> 25000 | M91: =F91*L91 -> 75000 | N91: =F91*K91 -> 60000 | O91: =M91-N91 -> 15000 | P91: =O91/M91 -> 0.2 | Q91: Low Profit
A92: O00091 | B92: 45734 | C92: =TEXT(B92,"MMMM") -> March | D92: C0194 | E92: P009 | F92: 2 | G92: Mohan Das | I92: Speaker | J92: =_xlfn.XLOOKUP(E92, Product_Master!$A$2:$A$101, Product_Master!$C$2:$C$101) -> Accessories | K92: =_xlfn.XLOOKUP(E92, Product_Master!$A$2:$A$101, Product_Master!$D$2:$D$101) -> 2000 | L92: =_xlfn.XLOOKUP(E92, Product_Master!$A$2:$A$101, Product_Master!$E$2:$E$101) -> 3000 | M92: =F92*L92 -> 6000 | N92: =F92*K92 -> 4000 | O92: =M92-N92 -> 2000 | P92: =O92/M92 -> 0.33333333 | Q92: High Profit
A93: O00092 | B93: 45721 | C93: =TEXT(B93,"MMMM") -> March | D93: C0235 | E93: P001 | F93: 4 | G93: Neha Singh | H93: Delhi | I93: Mobile | J93: =_xlfn.XLOOKUP(E93, Product_Master!$A$2:$A$101, Product_Master!$C$2:$C$101) -> Electronics | K93: =_xlfn.XLOOKUP(E93, Product_Master!$A$2:$A$101, Product_Master!$D$2:$D$101) -> 20000 | L93: =_xlfn.XLOOKUP(E93, Product_Master!$A$2:$A$101, Product_Master!$E$2:$E$101) -> 25000 | M93: =F93*L93 -> 100000 | N93: =F93*K93 -> 80000 | O93: =M93-N93 -> 20000 | P93: =O93/M93 -> 0.2 | Q93: Low Profit
A94: O00093 | B94: 45881 | C94: =TEXT(B94,"MMMM") -> August | D94: C0049 | E94: P062 | F94: 1 | G94: Neha Singh | H94: Pune | I94: Mouse | J94: =_xlfn.XLOOKUP(E94, Product_Master!$A$2:$A$101, Product_Master!$C$2:$C$101) -> Accessories | K94: =_xlfn.XLOOKUP(E94, Product_Master!$A$2:$A$101, Product_Master!$D$2:$D$101) -> 500 | L94: =_xlfn.XLOOKUP(E94, Product_Master!$A$2:$A$101, Product_Master!$E$2:$E$101) -> 800 | M94: =F94*L94 -> 800 | N94: =F94*K94 -> 500 | O94: =M94-N94 -> 300 | P94: =O94/M94 -> 0.375 | Q94: High Profit
A95: O00094 | B95: 45961 | C95: =TEXT(B95,"MMMM") -> October | D95: C0089 | E95: P058 | F95: 1 | G95: Meena Joshi | H95: Chandigarh | I95: Keyboard | J95: =_xlfn.XLOOKUP(E95, Product_Master!$A$2:$A$101, Product_Master!$C$2:$C$101) -> Accessories | K95: =_xlfn.XLOOKUP(E95, Product_Master!$A$2:$A$101, Product_Master!$D$2:$D$101) -> 900 | L95: =_xlfn.XLOOKUP(E95, Product_Master!$A$2:$A$101, Product_Master!$E$2:$E$101) -> 1500 | M95: =F95*L95 -> 1500 | N95: =F95*K95 -> 900 | O95: =M95-N95 -> 600 | P95: =O95/M95 -> 0.4 | Q95: High Profit
A96: O00095 | B96: 45807 | C96: =TEXT(B96,"MMMM") -> May | D96: C0275 | E96: P003 | F96: 2 | G96: Arjun Mehta | I96: Keyboard | J96: =_xlfn.XLOOKUP(E96, Product_Master!$A$2:$A$101, Product_Master!$C$2:$C$101) -> Accessories | K96: =_xlfn.XLOOKUP(E96, Product_Master!$A$2:$A$101, Product_Master!$D$2:$D$101) -> 900 | L96: =_xlfn.XLOOKUP(E96, Product_Master!$A$2:$A$101, Product_Master!$E$2:$E$101) -> 1500 | M96: =F96*L96 -> 3000 | N96: =F96*K96 -> 1800 | O96: =M96-N96 -> 1200 | P96: =O96/M96 -> 0.4 | Q96: High Profit
A97: O00096 | B97: 46005 | C97: =TEXT(B97,"MMMM") -> December | D97: C0260 | E97: P047 | F97: 2 | G97: Mohan Das | H97: Lucknow | I97: Speaker | J97: =_xlfn.XLOOKUP(E97, Product_Master!$A$2:$A$101, Product_Master!$C$2:$C$101) -> Accessories | K97: =_xlfn.XLOOKUP(E97, Product_Master!$A$2:$A$101, Product_Master!$D$2:$D$101) -> 2000 | L97: =_xlfn.XLOOKUP(E97, Product_Master!$A$2:$A$101, Product_Master!$E$2:$E$101) -> 3000 | M97: =F97*L97 -> 6000 | N97: =F97*K97 -> 4000 | O97: =M97-N97 -> 2000 | P97: =O97/M97 -> 0.33333333 | Q97: High Profit
A98: O00097 | B98: 45809 | C98: =TEXT(B98,"MMMM") -> June | D98: C0072 | E98: P014 | F98: 5 | G98: Arjun Mehta | H98: Pune | I98: Mouse | J98: =_xlfn.XLOOKUP(E98, Product_Master!$A$2:$A$101, Product_Master!$C$2:$C$101) -> Accessories | K98: =_xlfn.XLOOKUP(E98, Product_Master!$A$2:$A$101, Product_Master!$D$2:$D$101) -> 500 | L98: =_xlfn.XLOOKUP(E98, Product_Master!$A$2:$A$101, Product_Master!$E$2:$E$101) -> 800 | M98: =F98*L98 -> 4000 | N98: =F98*K98 -> 2500 | O98: =M98-N98 -> 1500 | P98: =O98/M98 -> 0.375 | Q98: High Profit
A99: O00098 | B99: 46002 | C99: =TEXT(B99,"MMMM") -> December | D99: C0269 | E99: P005 | F99: 5 | G99: Neha Singh | H99: Chandigarh | I99: Mouse | J99: =_xlfn.XLOOKUP(E99, Product_Master!$A$2:$A$101, Product_Master!$C$2:$C$101) -> Accessories | K99: =_xlfn.XLOOKUP(E99, Product_Master!$A$2:$A$101, Product_Master!$D$2:$D$101) -> 500 | L99: =_xlfn.XLOOKUP(E99, Product_Master!$A$2:$A$101, Product_Master!$E$2:$E$101) -> 800 | M99: =F99*L99 -> 4000 | N99: =F99*K99 -> 2500 | O99: =M99-N99 -> 1500 | P99: =O99/M99 -> 0.375 | Q99: High Profit
A100: O00099 | B100: 45936 | C100: =TEXT(B100,"MMMM") -> October | D100: C0140 | E100: P095 | F100: 3 | G100: Arjun Mehta | H100: Mumbai | I100: Mobile | J100: =_xlfn.XLOOKUP(E100, Product_Master!$A$2:$A$101, Product_Master!$C$2:$C$101) -> Electronics | K100: =_xlfn.XLOOKUP(E100, Product_Master!$A$2:$A$101, Product_Master!$D$2:$D$101) -> 20000 | L100: =_xlfn.XLOOKUP(E100, Product_Master!$A$2:$A$101, Product_Master!$E$2:$E$101) -> 25000 | M100: =F100*L100 -> 75000 | N100: =F100*K100 -> 60000 | O100: =M100-N100 -> 15000 | P100: =O100/M100 -> 0.2 | Q100: Low Profit
A101: O00100 | B101: 45742 | C101: =TEXT(B101,"MMMM") -> March | D101: C0205 | E101: P057 | F101: 4 | G101: Vikas Yadav | H101: Noida | I101: Laptop | J101: =_xlfn.XLOOKUP(E101, Product_Master!$A$2:$A$101, Product_Master!$C$2:$C$101) -> Electronics | K101: =_xlfn.XLOOKUP(E101, Product_Master!$A$2:$A$101, Product_Master!$D$2:$D$101) -> 42000 | L101: =_xlfn.XLOOKUP(E101, Product_Master!$A$2:$A$101, Product_Master!$E$2:$E$101) -> 50000 | M101: =F101*L101 -> 200000 | N101: =F101*K101 -> 168000 | O101: =M101-N101 -> 32000 | P101: =O101/M101 -> 0.16 | Q101: Low Profit
A102: O00101 | B102: 45955 | C102: =TEXT(B102,"MMMM") -> October | D102: C0289 | E102: P093 | F102: 1 | G102: Priya Verma | H102: Mumbai | I102: Printer | J102: =_xlfn.XLOOKUP(E102, Product_Master!$A$2:$A$101, Product_Master!$C$2:$C$101) -> Electronics | K102: =_xlfn.XLOOKUP(E102, Product_Master!$A$2:$A$101, Product_Master!$D$2:$D$101) -> 12000 | L102: =_xlfn.XLOOKUP(E102, Product_Master!$A$2:$A$101, Product_Master!$E$2:$E$101) -> 15000 | M102: =F102*L102 -> 15000 | N102: =F102*K102 -> 12000 | O102: =M102-N102 -> 3000 | P102: =O102/M102 -> 0.2 | Q102: Low Profit
A103: O00102 | B103: 45831 | C103: =TEXT(B103,"MMMM") -> June | D103: C0071 | E103: P049 | F103: 1 | G103: Karan Patel | H103: Jaipur | I103: Speaker | J103: =_xlfn.XLOOKUP(E103, Product_Master!$A$2:$A$101, Product_Master!$C$2:$C$101) -> Accessories | K103: =_xlfn.XLOOKUP(E103, Product_Master!$A$2:$A$101, Product_Master!$D$2:$D$101) -> 2000 | L103: =_xlfn.XLOOKUP(E103, Product_Master!$A$2:$A$101, Product_Master!$E$2:$E$101) -> 3000 | M103: =F103*L103 -> 3000 | N103: =F103*K103 -> 2000 | O103: =M103-N103 -> 1000 | P103: =O103/M103 -> 0.33333333 | Q103: High Profit
A104: O00103 | B104: 45761 | C104: =TEXT(B104,"MMMM") -> April | D104: C0219 | E104: P019 | F104: 3 | G104: Riya Sharma | H104: Lucknow | I104: Laptop | J104: =_xlfn.XLOOKUP(E104, Product_Master!$A$2:$A$101, Product_Master!$C$2:$C$101) -> Electronics | K104: =_xlfn.XLOOKUP(E104, Product_Master!$A$2:$A$101, Product_Master!$D$2:$D$101) -> 42000 | L104: =_xlfn.XLOOKUP(E104, Product_Master!$A$2:$A$101, Product_Master!$E$2:$E$101) -> 50000 | M104: =F104*L104 -> 150000 | N104: =F104*K104 -> 126000 | O104: =M104-N104 -> 24000 | P104: =O104/M104 -> 0.16 | Q104: Low Profit
A105: O00104 | B105: 46021 | C105: =TEXT(B105,"MMMM") -> December | D105: C0204 | E105: P005 | F105: 5 | G105: Meena Joshi | H105: Jaipur | I105: Mouse | J105: =_xlfn.XLOOKUP(E105, Product_Master!$A$2:$A$101, Product_Master!$C$2:$C$101) -> Accessories | K105: =_xlfn.XLOOKUP(E105, Product_Master!$A$2:$A$101, Product_Master!$D$2:$D$101) -> 500 | L105: =_xlfn.XLOOKUP(E105, Product_Master!$A$2:$A$101, Product_Master!$E$2:$E$101) -> 800 | M105: =F105*L105 -> 4000 | N105: =F105*K105 -> 2500 | O105: =M105-N105 -> 1500 | P105: =O105/M105 -> 0.375 | Q105: High Profit
A106: O00105 | B106: 45808 | C106: =TEXT(B106,"MMMM") -> May | D106: C0132 | E106: P063 | F106: 4 | G106: Priya Verma | H106: Lucknow | I106: Speaker | J106: =_xlfn.XLOOKUP(E106, Product_Master!$A$2:$A$101, Product_Master!$C$2:$C$101) -> Accessories | K106: =_xlfn.XLOOKUP(E106, Product_Master!$A$2:$A$101, Product_Master!$D$2:$D$101) -> 2000 | L106: =_xlfn.XLOOKUP(E106, Product_Master!$A$2:$A$101, Product_Master!$E$2:$E$101) -> 3000 | M106: =F106*L106 -> 12000 | N106: =F106*K106 -> 8000 | O106: =M106-N106 -> 4000 | P106: =O106/M106 -> 0.33333333 | Q106: High Profit
A107: O00106 | B107: 45947 | C107: =TEXT(B107,"MMMM") -> October | D107: C0292 | E107: P088 | F107: 1 | G107: Anjali Gupta | H107: Mumbai | I107: Mouse | J107: =_xlfn.XLOOKUP(E107, Product_Master!$A$2:$A$101, Product_Master!$C$2:$C$101) -> Accessories | K107: =_xlfn.XLOOKUP(E107, Product_Master!$A$2:$A$101, Product_Master!$D$2:$D$101) -> 500 | L107: =_xlfn.XLOOKUP(E107, Product_Master!$A$2:$A$101, Product_Master!$E$2:$E$101) -> 800 | M107: =F107*L107 -> 800 | N107: =F107*K107 -> 500 | O107: =M107-N107 -> 300 | P107: =O107/M107 -> 0.375 | Q107: High Profit
A108: O00107 | B108: 45962 | C108: =TEXT(B108,"MMMM") -> November | D108: C0087 | E108: P033 | F108: 1 | G108: Priya Verma | H108: Ahmedabad | I108: Laptop | J108: =_xlfn.XLOOKUP(E108, Product_Master!$A$2:$A$101, Product_Master!$C$2:$C$101) -> Electronics | K108: =_xlfn.XLOOKUP(E108, Product_Master!$A$2:$A$101, Product_Master!$D$2:$D$101) -> 42000 | L108: =_xlfn.XLOOKUP(E108, Product_Master!$A$2:$A$101, Product_Master!$E$2:$E$101) -> 50000 | M108: =F108*L108 -> 50000 | N108: =F108*K108 -> 42000 | O108: =M108-N108 -> 8000 | P108: =O108/M108 -> 0.16 | Q108: Low Profit
A109: O00108 | B109: 45822 | C109: =TEXT(B109,"MMMM") -> June | D109: C0227 | E109: P035 | F109: 3 | G109: Riya Sharma | H109: Mumbai | I109: Monitor | J109: =_xlfn.XLOOKUP(E109, Product_Master!$A$2:$A$101, Product_Master!$C$2:$C$101) -> Accessories | K109: =_xlfn.XLOOKUP(E109, Product_Master!$A$2:$A$101, Product_Master!$D$2:$D$101) -> 9000 | L109: =_xlfn.XLOOKUP(E109, Product_Master!$A$2:$A$101, Product_Master!$E$2:$E$101) -> 12000 | M109: =F109*L109 -> 36000 | N109: =F109*K109 -> 27000 | O109: =M109-N109 -> 9000 | P109: =O109/M109 -> 0.25 | Q109: High Profit
A110: O00109 | B110: 45814 | C110: =TEXT(B110,"MMMM") -> June | D110: C0194 | E110: P060 | F110: 3 | G110: Mohan Das | I110: Mouse | J110: =_xlfn.XLOOKUP(E110, Product_Master!$A$2:$A$101, Product_Master!$C$2:$C$101) -> Accessories | K110: =_xlfn.XLOOKUP(E110, Product_Master!$A$2:$A$101, Product_Master!$D$2:$D$101) -> 500 | L110: =_xlfn.XLOOKUP(E110, Product_Master!$A$2:$A$101, Product_Master!$E$2:$E$101) -> 800 | M110: =F110*L110 -> 2400 | N110: =F110*K110 -> 1500 | O110: =M110-N110 -> 900 | P110: =O110/M110 -> 0.375 | Q110: High Profit
A111: O00110 | B111: 45663 | C111: =TEXT(B111,"MMMM") -> January | D111: C0250 | E111: P018 | F111: 3 | G111: Arjun Mehta | H111: Pune | I111: Laptop | J111: =_xlfn.XLOOKUP(E111, Product_Master!$A$2:$A$101, Product_Master!$C$2:$C$101) -> Electronics | K111: =_xlfn.XLOOKUP(E111, Product_Master!$A$2:$A$101, Product_Master!$D$2:$D$101) -> 42000 | L111: =_xlfn.XLOOKUP(E111, Product_Master!$A$2:$A$101, Product_Master!$E$2:$E$101) -> 50000 | M111: =F111*L111 -> 150000 | N111: =F111*K111 -> 126000 | O111: =M111-N111 -> 24000 | P111: =O111/M111 -> 0.16 | Q111: Low Profit
A112: O00111 | B112: 45867 | C112: =TEXT(B112,"MMMM") -> July | D112: C0277 | E112: P065 | F112: 3 | G112: Arjun Mehta | H112: Noida | I112: Mouse | J112: =_xlfn.XLOOKUP(E112, Product_Master!$A$2:$A$101, Product_Master!$C$2:$C$101) -> Accessories | K112: =_xlfn.XLOOKUP(E112, Product_Master!$A$2:$A$101, Product_Master!$D$2:$D$101) -> 500 | L112: =_xlfn.XLOOKUP(E112, Product_Master!$A$2:$A$101, Product_Master!$E$2:$E$101) -> 800 | M112: =F112*L112 -> 2400 | N112: =F112*K112 -> 1500 | O112: =M112-N112 -> 900 | P112: =O112/M112 -> 0.375 | Q112: High Profit
A113: O00112 | B113: 45753 | C113: =TEXT(B113,"MMMM") -> April | D113: C0082 | E113: P053 | F113: 3 | G113: Meena Joshi | H113: Jaipur | I113: Laptop | J113: =_xlfn.XLOOKUP(E113, Product_Master!$A$2:$A$101, Product_Master!$C$2:$C$101) -> Electronics | K113: =_xlfn.XLOOKUP(E113, Product_Master!$A$2:$A$101, Product_Master!$D$2:$D$101) -> 42000 | L113: =_xlfn.XLOOKUP(E113, Product_Master!$A$2:$A$101, Product_Master!$E$2:$E$101) -> 50000 | M113: =F113*L113 -> 150000 | N113: =F113*K113 -> 126000 | O113: =M113-N113 -> 24000 | P113: =O113/M113 -> 0.16 | Q113: Low Profit
A114: O00113 | B114: 45997 | C114: =TEXT(B114,"MMMM") -> December | D114: C0193 | E114: P010 | F114: 3 | G114: Karan Patel | H114: Mumbai | I114: Monitor | J114: =_xlfn.XLOOKUP(E114, Product_Master!$A$2:$A$101, Product_Master!$C$2:$C$101) -> Accessories | K114: =_xlfn.XLOOKUP(E114, Product_Master!$A$2:$A$101, Product_Master!$D$2:$D$101) -> 9000 | L114: =_xlfn.XLOOKUP(E114, Product_Master!$A$2:$A$101, Product_Master!$E$2:$E$101) -> 12000 | M114: =F114*L114 -> 36000 | N114: =F114*K114 -> 27000 | O114: =M114-N114 -> 9000 | P114: =O114/M114 -> 0.25 | Q114: High Profit
A115: O00114 | B115: 45934 | C115: =TEXT(B115,"MMMM") -> October | D115: C0250 | E115: P010 | F115: 4 | G115: Arjun Mehta | H115: Pune | I115: Monitor | J115: =_xlfn.XLOOKUP(E115, Product_Master!$A$2:$A$101, Product_Master!$C$2:$C$101) -> Accessories | K115: =_xlfn.XLOOKUP(E115, Product_Master!$A$2:$A$101, Product_Master!$D$2:$D$101) -> 9000 | L115: =_xlfn.XLOOKUP(E115, Product_Master!$A$2:$A$101, Product_Master!$E$2:$E$101) -> 12000 | M115: =F115*L115 -> 48000 | N115: =F115*K115 -> 36000 | O115: =M115-N115 -> 12000 | P115: =O115/M115 -> 0.25 | Q115: High Profit
A116: O00115 | B116: 45715 | C116: =TEXT(B116,"MMMM") -> February | D116: C0261 | E116: P067 | F116: 1 | G116: Rahul Sharma | H116: Mumbai | I116: Printer | J116: =_xlfn.XLOOKUP(E116, Product_Master!$A$2:$A$101, Product_Master!$C$2:$C$101) -> Electronics | K116: =_xlfn.XLOOKUP(E116, Product_Master!$A$2:$A$101, Product_Master!$D$2:$D$101) -> 12000 | L116: =_xlfn.XLOOKUP(E116, Product_Master!$A$2:$A$101, Product_Master!$E$2:$E$101) -> 15000 | M116: =F116*L116 -> 15000 | N116: =F116*K116 -> 12000 | O116: =M116-N116 -> 3000 | P116: =O116/M116 -> 0.2 | Q116: Low Profit
A117: O00116 | B117: 45664 | C117: =TEXT(B117,"MMMM") -> January | D117: C0011 | E117: P012 | F117: 4 | G117: Amit Kumar | H117: Ahmedabad | I117: Keyboard | J117: =_xlfn.XLOOKUP(E117, Product_Master!$A$2:$A$101, Product_Master!$C$2:$C$101) -> Accessories | K117: =_xlfn.XLOOKUP(E117, Product_Master!$A$2:$A$101, Product_Master!$D$2:$D$101) -> 900 | L117: =_xlfn.XLOOKUP(E117, Product_Master!$A$2:$A$101, Product_Master!$E$2:$E$101) -> 1500 | M117: =F117*L117 -> 6000 | N117: =F117*K117 -> 3600 | O117: =M117-N117 -> 2400 | P117: =O117/M117 -> 0.4 | Q117: High Profit
A118: O00117 | B118: 45901 | C118: =TEXT(B118,"MMMM") -> September | D118: C0143 | E118: P054 | F118: 5 | G118: Anjali Gupta | H118: Pune | I118: Keyboard | J118: =_xlfn.XLOOKUP(E118, Product_Master!$A$2:$A$101, Product_Master!$C$2:$C$101) -> Accessories | K118: =_xlfn.XLOOKUP(E118, Product_Master!$A$2:$A$101, Product_Master!$D$2:$D$101) -> 900 | L118: =_xlfn.XLOOKUP(E118, Product_Master!$A$2:$A$101, Product_Master!$E$2:$E$101) -> 1500 | M118: =F118*L118 -> 7500 | N118: =F118*K118 -> 4500 | O118: =M118-N118 -> 3000 | P118: =O118/M118 -> 0.4 | Q118: High Profit
A119: O00118 | B119: 46016 | C119: =TEXT(B119,"MMMM") -> December | D119: C0116 | E119: P040 | F119: 5 | G119: Meena Joshi | H119: Chandigarh | I119: Laptop | J119: =_xlfn.XLOOKUP(E119, Product_Master!$A$2:$A$101, Product_Master!$C$2:$C$101) -> Electronics | K119: =_xlfn.XLOOKUP(E119, Product_Master!$A$2:$A$101, Product_Master!$D$2:$D$101) -> 42000 | L119: =_xlfn.XLOOKUP(E119, Product_Master!$A$2:$A$101, Product_Master!$E$2:$E$101) -> 50000 | M119: =F119*L119 -> 250000 | N119: =F119*K119 -> 210000 | O119: =M119-N119 -> 40000 | P119: =O119/M119 -> 0.16 | Q119: Low Profit
A120: O00119 | B120: 45719 | C120: =TEXT(B120,"MMMM") -> March | D120: C0246 | E120: P012 | F120: 4 | G120: Meena Joshi | H120: Pune | I120: Keyboard | J120: =_xlfn.XLOOKUP(E120, Product_Master!$A$2:$A$101, Product_Master!$C$2:$C$101) -> Accessories | K120: =_xlfn.XLOOKUP(E120, Product_Master!$A$2:$A$101, Product_Master!$D$2:$D$101) -> 900 | L120: =_xlfn.XLOOKUP(E120, Product_Master!$A$2:$A$101, Product_Master!$E$2:$E$101) -> 1500 | M120: =F120*L120 -> 6000 | N120: =F120*K120 -> 3600 | O120: =M120-N120 -> 2400 | P120: =O120/M120 -> 0.4 | Q120: High Profit
A121: O00120 | B121: 45814 | C121: =TEXT(B121,"MMMM") -> June | D121: C0254 | E121: P096 | F121: 3 | G121: Vikas Yadav | H121: Lucknow | I121: Printer | J121: =_xlfn.XLOOKUP(E121, Product_Master!$A$2:$A$101, Product_Master!$C$2:$C$101) -> Electronics | K121: =_xlfn.XLOOKUP(E121, Product_Master!$A$2:$A$101, Product_Master!$D$2:$D$101) -> 12000 | L121: =_xlfn.XLOOKUP(E121, Product_Master!$A$2:$A$101, Product_Master!$E$2:$E$101) -> 15000 | M121: =F121*L121 -> 45000 | N121: =F121*K121 -> 36000 | O121: =M121-N121 -> 9000 | P121: =O121/M121 -> 0.2 | Q121: Low Profit
A122: O00121 | B122: 45768 | C122: =TEXT(B122,"MMMM") -> April | D122: C0189 | E122: P007 | F122: 4 | G122: Rahul Sharma | H122: Lucknow | I122: Mobile | J122: =_xlfn.XLOOKUP(E122, Product_Master!$A$2:$A$101, Product_Master!$C$2:$C$101) -> Electronics | K122: =_xlfn.XLOOKUP(E122, Product_Master!$A$2:$A$101, Product_Master!$D$2:$D$101) -> 20000 | L122: =_xlfn.XLOOKUP(E122, Product_Master!$A$2:$A$101, Product_Master!$E$2:$E$101) -> 25000 | M122: =F122*L122 -> 100000 | N122: =F122*K122 -> 80000 | O122: =M122-N122 -> 20000 | P122: =O122/M122 -> 0.2 | Q122: Low Profit
... A140: O00139 | B140: 45955 | C140: =TEXT(B140,"MMMM") -> October | D140: C0107 | E140: P099 | F140: 4 | G140: Amit Kumar | H140: Lucknow | I140: Keyboard | J140: =_xlfn.XLOOKUP(E140, Product_Master!$A$2:$A$101, Product_Master!$C$2:$C$101) -> Accessories | K140: =_xlfn.XLOOKUP(E140, Product_Master!$A$2:$A$101, Product_Master!$D$2:$D$101) -> 900 | L140: =_xlfn.XLOOKUP(E140, Product_Master!$A$2:$A$101, Product_Master!$E$2:$E$101) -> 1500 | M140: =F140*L140 -> 6000 | N140: =F140*K140 -> 3600 | O140: =M140-N140 -> 2400 | P140: =O140/M140 -> 0.4 | Q140: High Profit
A141: O00140 | B141: 45676 | C141: =TEXT(B141,"MMMM") -> January | D141: C9999 | E141: P001 | F141: 1 | G141: Invailid | I141: Mobile | J141: =_xlfn.XLOOKUP(E141, Product_Master!$A$2:$A$101, Product_Master!$C$2:$C$101) -> Electronics | K141: =_xlfn.XLOOKUP(E141, Product_Master!$A$2:$A$101, Product_Master!$D$2:$D$101) -> 20000 | L141: =_xlfn.XLOOKUP(E141, Product_Master!$A$2:$A$101, Product_Master!$E$2:$E$101) -> 25000 | M141: =F141*L141 -> 25000 | N141: =F141*K141 -> 20000 | O141: =M141-N141 -> 5000 | P141: =O141/M141 -> 0.2 | Q141: Low Profit
A142: O00141 | B142: 45971 | C142: =TEXT(B142,"MMMM") -> November | D142: C0186 | E142: P037 | F142: 2 | G142: Anjali Gupta | H142: Pune | I142: Printer | J142: =_xlfn.XLOOKUP(E142, Product_Master!$A$2:$A$101, Product_Master!$C$2:$C$101) -> Electronics | K142: =_xlfn.XLOOKUP(E142, Product_Master!$A$2:$A$101, Product_Master!$D$2:$D$101) -> 12000 | L142: =_xlfn.XLOOKUP(E142, Product_Master!$A$2:$A$101, Product_Master!$E$2:$E$101) -> 15000 | M142: =F142*L142 -> 30000 | N142: =F142*K142 -> 24000 | O142: =M142-N142 -> 6000 | P142: =O142/M142 -> 0.2 | Q142: Low Profit
A143: O00142 | B143: 45666 | C143: =TEXT(B143,"MMMM") -> January | D143: C0007 | E143: P072 | F143: 2 | G143: Neha Singh | H143: Lucknow | I143: Mobile | J143: =_xlfn.XLOOKUP(E143, Product_Master!$A$2:$A$101, Product_Master!$C$2:$C$101) -> Electronics | K143: =_xlfn.XLOOKUP(E143, Product_Master!$A$2:$A$101, Product_Master!$D$2:$D$101) -> 20000 | L143: =_xlfn.XLOOKUP(E143, Product_Master!$A$2:$A$101, Product_Master!$E$2:$E$101) -> 25000 | M143: =F143*L143 -> 50000 | N143: =F143*K143 -> 40000 | O143: =M143-N143 -> 10000 | P143: =O143/M143 -> 0.2 | Q143: Low Profit
A144: O00143 | B144: 45740 | C144: =TEXT(B144,"MMMM") -> March | D144: C0224 | E144: P085 | F144: 1 | G144: Riya Sharma | H144: Pune | I144: Keyboard | J144: =_xlfn.XLOOKUP(E144, Product_Master!$A$2:$A$101, Product_Master!$C$2:$C$101) -> Accessories | K144: =_xlfn.XLOOKUP(E144, Product_Master!$A$2:$A$101, Product_Master!$D$2:$D$101) -> 900 | L144: =_xlfn.XLOOKUP(E144, Product_Master!$A$2:$A$101, Product_Master!$E$2:$E$101) -> 1500 | M144: =F144*L144 -> 1500 | N144: =F144*K144 -> 900 | O144: =M144-N144 -> 600 | P144: =O144/M144 -> 0.4 | Q144: High Profit
A145: O00144 | B145: 45875 | C145: =TEXT(B145,"MMMM") -> August | D145: C9999 | E145: P006 | F145: 3 | G145: Invailid | I145: Laptop | J145: =_xlfn.XLOOKUP(E145, Product_Master!$A$2:$A$101, Product_Master!$C$2:$C$101) -> Electronics | K145: =_xlfn.XLOOKUP(E145, Product_Master!$A$2:$A$101, Product_Master!$D$2:$D$101) -> 42000 | L145: =_xlfn.XLOOKUP(E145, Product_Master!$A$2:$A$101, Product_Master!$E$2:$E$101) -> 50000 | M145: =F145*L145 -> 150000 | N145: =F145*K145 -> 126000 | O145: =M145-N145 -> 24000 | P145: =O145/M145 -> 0.16 | Q145: Low Profit
A146: O00145 | B146: 45835 | C146: =TEXT(B146,"MMMM") -> June | D146: C0061 | E146: P036 | F146: 3 | G146: Arjun Mehta | H146: Mumbai | I146: Mobile | J146: =_xlfn.XLOOKUP(E146, Product_Master!$A$2:$A$101, Product_Master!$C$2:$C$101) -> Electronics | K146: =_xlfn.XLOOKUP(E146, Product_Master!$A$2:$A$101, Product_Master!$D$2:$D$101) -> 20000 | L146: =_xlfn.XLOOKUP(E146, Product_Master!$A$2:$A$101, Product_Master!$E$2:$E$101) -> 25000 | M146: =F146*L146 -> 75000 | N146: =F146*K146 -> 60000 | O146: =M146-N146 -> 15000 | P146: =O146/M146 -> 0.2 | Q146: Low Profit
A147: O00146 | B147: 45896 | C147: =TEXT(B147,"MMMM") -> August | D147: C0173 | E147: P064 | F147: 1 | G147: Mohan Das | H147: Pune | I147: Mobile | J147: =_xlfn.XLOOKUP(E147, Product_Master!$A$2:$A$101, Product_Master!$C$2:$C$101) -> Electronics | K147: =_xlfn.XLOOKUP(E147, Product_Master!$A$2:$A$101, Product_Master!$D$2:$D$101) -> 20000 | L147: =_xlfn.XLOOKUP(E147, Product_Master!$A$2:$A$101, Product_Master!$E$2:$E$101) -> 25000 | M147: =F147*L147 -> 25000 | N147: =F147*K147 -> 20000 | O147: =M147-N147 -> 5000 | P147: =O147/M147 -> 0.2 | Q147: Low Profit
A148: O00147 | B148: 45786 | C148: =TEXT(B148,"MMMM") -> May | D148: C0075 | E148: P028 | F148: 5 | G148: Mohan Das | H148: Jaipur | I148: Laptop | J148: =_xlfn.XLOOKUP(E148, Product_Master!$A$2:$A$101, Product_Master!$C$2:$C$101) -> Electronics | K148: =_xlfn.XLOOKUP(E148, Product_Master!$A$2:$A$101, Product_Master!$D$2:$D$101) -> 42000 | L148: =_xlfn.XLOOKUP(E148, Product_Master!$A$2:$A$101, Product_Master!$E$2:$E$101) -> 50000 | M148: =F148*L148 -> 250000 | N148: =F148*K148 -> 210000 | O148: =M148-N148 -> 40000 | P148: =O148/M148 -> 0.16 | Q148: Low Profit
A149: O00148 | B149: 45678 | C149: =TEXT(B149,"MMMM") -> January | D149: C0206 | E149: P012 | F149: 3 | G149: Priya Verma | H149: Lucknow | I149: Keyboard | J149: =_xlfn.XLOOKUP(E149, Product_Master!$A$2:$A$101, Product_Master!$C$2:$C$101) -> Accessories | K149: =_xlfn.XLOOKUP(E149, Product_Master!$A$2:$A$101, Product_Master!$D$2:$D$101) -> 900 | L149: =_xlfn.XLOOKUP(E149, Product_Master!$A$2:$A$101, Product_Master!$E$2:$E$101) -> 1500 | M149: =F149*L149 -> 4500 | N149: =F149*K149 -> 2700 | O149: =M149-N149 -> 1800 | P149: =O149/M149 -> 0.4 | Q149: High Profit
A150: O00149 | B150: 45930 | C150: =TEXT(B150,"MMMM") -> September | D150: C0156 | E150: P047 | F150: 3 | G150: Sneha Roy | H150: Lucknow | I150: Speaker | J150: =_xlfn.XLOOKUP(E150, Product_Master!$A$2:$A$101, Product_Master!$C$2:$C$101) -> Accessories | K150: =_xlfn.XLOOKUP(E150, Product_Master!$A$2:$A$101, Product_Master!$D$2:$D$101) -> 2000 | L150: =_xlfn.XLOOKUP(E150, Product_Master!$A$2:$A$101, Product_Master!$E$2:$E$101) -> 3000 | M150: =F150*L150 -> 9000 | N150: =F150*K150 -> 6000 | O150: =M150-N150 -> 3000 | P150: =O150/M150 -> 0.33333333 | Q150: High Profit
A151: O00150 | B151: 45728 | C151: =TEXT(B151,"MMMM") -> March | D151: C0074 | E151: P100 | F151: 5 | G151: Riya Sharma | H151: Chandigarh | I151: Speaker | J151: =_xlfn.XLOOKUP(E151, Product_Master!$A$2:$A$101, Product_Master!$C$2:$C$101) -> Accessories | K151: =_xlfn.XLOOKUP(E151, Product_Master!$A$2:$A$101, Product_Master!$D$2:$D$101) -> 2000 | L151: =_xlfn.XLOOKUP(E151, Product_Master!$A$2:$A$101, Product_Master!$E$2:$E$101) -> 3000 | M151: =F151*L151 -> 15000 | N151: =F151*K151 -> 10000 | O151: =M151-N151 -> 5000 | P151: =O151/M151 -> 0.33333333 | Q151: High Profit
...

Sheet Analysis
E4: KPI | F4: Value
E6: Total Revenue | F6: =SUM(Clean_Data!M2:M1001) -> 47763300
E7: Total Profit | F7: =SUM(Clean_Data!O2:O1001) -> 9157700
E8: Profit Margin % | F8: =F7/F6 -> 0.19173089
E9: Total Orders | F9: =COUNTA(Clean_Data!A2:A1001) -> 1000
E10: Total Quantity Sold | F10: =SUM(Clean_Data!F2:F1001) -> 3031
E11: Avarage Order Value | F11: =AVERAGE(Clean_Data!M2:M1001) -> 47763.3
E12: Highest Order | F12: =MAX(Clean_Data!M2:M1001) -> 250000
E13: Lowest Order | F13: =MIN(Clean_Data!M3:M1002) -> 800
E14: Top Product | F14: =_xlfn.XLOOKUP(LARGE(Clean_Data!M2:M1001,1 ),Clean_Data!M2:M1001,Clean_Data!I2:I1001) -> Laptop
E15: Top Customer | F15: Riya sharma
E16: Top City | F16: Jaipur

Sheet Dashboard
A1: Build Dashboard Here
B3: Retail Store Sales Dashboard
U6: Business Insights
U9: ✔ Laptop generated highest revenue.
U11: ✔ Riya Sharma achieved highest sales.
U13: ✔ Jaipur is the top performing city.
U15: ✔ Electronics contributes 78% of total revenue.
U17: ✔ Revenue and Profit are highest in Jan ,mar , Des .
